jupyterlab_favorites/__init__.py
jupyterlab_favorites/_version.py
jupyterlab_favorites-3.4.0.data/data/share/jupyter/labextensions/@jlab-enhanced/favorites/package.json
jupyterlab_favorites-3.4.0.data/data/share/jupyter/labextensions/@jlab-enhanced/favorites/schemas/@jlab-enhanced/favorites/favorites.json
jupyterlab_favorites-3.4.0.data/data/share/jupyter/labextensions/@jlab-enhanced/favorites/schemas/@jlab-enhanced/favorites/package.json.orig
jupyterlab_favorites-3.4.0.data/data/share/jupyter/labextensions/@jlab-enhanced/favorites/static/693.23f8a964279cc92cab6d.js
jupyterlab_favorites-3.4.0.data/data/share/jupyter/labextensions/@jlab-enhanced/favorites/static/728.40d48f804b5605a3bb41.js
jupyterlab_favorites-3.4.0.data/data/share/jupyter/labextensions/@jlab-enhanced/favorites/static/remoteEntry.d6f6707872497877b6e6.js
jupyterlab_favorites-3.4.0.data/data/share/jupyter/labextensions/@jlab-enhanced/favorites/static/style.js
jupyterlab_favorites-3.4.0.data/data/share/jupyter/labextensions/@jlab-enhanced/favorites/static/third-party-licenses.json
jupyterlab_favorites-3.4.0.data/data/share/jupyter/labextensions/@jlab-enhanced/favorites/install.json
jupyterlab_favorites-3.4.0.dist-info/METADATA
jupyterlab_favorites-3.4.0.dist-info/WHEEL
jupyterlab_favorites-3.4.0.dist-info/licenses/LICENSE
jupyterlab_favorites-3.4.0.dist-info/RECORD
