Metadata-Version: 2.4
Name: jupyterlab_favorites
Version: 3.4.0
Dynamic: Keywords
Summary: Add the ability to save favorite folders to JupyterLab for quicker browsing
Project-URL: Homepage, https://github.com/jupyterlab-contrib/jupyterlab-favorites
Project-URL: Bug Tracker, https://github.com/jupyterlab-contrib/jupyterlab-favorites/issues
Project-URL: Repository, https://github.com/jupyterlab-contrib/jupyterlab-favorites.git
Author: Trevor Slaton
License: Copyright (c) 2021, Frederic Collonval 
License-File: LICENSE
Classifier: Framework :: Jupyter
Classifier: Framework :: Jupyter :: JupyterLab
Classifier: Framework :: Jupyter :: JupyterLab :: 4
Classifier: Framework :: Jupyter :: JupyterLab :: Extensions
Classifier: Framework :: Jupyter :: JupyterLab :: Extensions :: Prebuilt
Classifier: License :: OSI Approved :: BSD License
Classifier: Programming Language :: Python
Classifier: Programming Language :: Python :: 3
Classifier: Programming Language :: Python :: 3.8
Classifier: Programming Language :: Python :: 3.9
Classifier: Programming Language :: Python :: 3.10
Classifier: Programming Language :: Python :: 3.11
Requires-Python: >=3.8
